npm_calmarendian_date/__init__.py
npm_calmarendian_date/c_date_config.py
npm_calmarendian_date/calmarendian_date.py
npm_calmarendian_date/date_elements.py
npm_calmarendian_date/string_conversions.py
npm_calmarendian_date/exceptions/__init__.py
npm_calmarendian_date/exceptions/date_exceptions.py
npm_calmarendian_date-0.3.0.dist-info/LICENSE
npm_calmarendian_date-0.3.0.dist-info/METADATA
npm_calmarendian_date-0.3.0.dist-info/WHEEL
npm_calmarendian_date-0.3.0.dist-info/top_level.txt
npm_calmarendian_date-0.3.0.dist-info/RECORD
