Metadata-Version: 2.1
Name: npm-calmarendian-date
Version: 0.3.0
Summary: A Date class for the Calendar of Lorelei
Home-page: https://github.com/natashamoorfield/npm_calmarendian_date
Author: Natasha Moorfield
Project-URL: Bug Tracker, https://github.com/natashamoorfield/npm_calmarendian_date/issues
Classifier: Programming Language :: Python :: 3
Classifier: Programming Language :: Python :: 3.8
Classifier: Programming Language :: Python :: 3.9
Classifier: Programming Language :: Python :: 3.10
Classifier: License :: OSI Approved :: GNU General Public License v3 or later (GPLv3+)
Classifier: Operating System :: OS Independent
Requires-Python: >=3.8
License-File: LICENSE
